lazysql/__init__.py
lazysql/lazy.py
tests/__init__.py
tests/test_lazy.py
lazysql-0.0.5.dist-info/LICENSE
lazysql-0.0.5.dist-info/METADATA
lazysql-0.0.5.dist-info/WHEEL
lazysql-0.0.5.dist-info/top_level.txt
lazysql-0.0.5.dist-info/RECORD
