Metadata-Version: 2.1
Name: lazysql
Version: 0.0.5
Summary: SQL connector for lazy people
Home-page: https://github.com/silvercondor/lazy-sql
Author: silvercondor
Author-email: silvercondor@protonmail.com
License: UNKNOWN
Platform: UNKNOWN
Classifier: Programming Language :: Python :: 3
Classifier: License :: OSI Approved :: MIT License
Classifier: Operating System :: OS Independent
Requires-Python: >=3.6
